Metadata-Version: 2.1
Name: dnms-probability
Version: 0.10
Summary: Gaussian and Binomial distributions
Author: James Oyebade
Author-email: jamesthepink@gmail.com
License-File: license.txt
